wikidata/__init__.py
wikidata/cache.py
wikidata/client.py
wikidata/commonsmedia.py
wikidata/datavalue.py
wikidata/entity.py
wikidata/globecoordinate.py
wikidata/multilingual.py
wikidata/py.typed
wikidata/quantity.py
Wikidata-0.8.1.dist-info/LICENSE
Wikidata-0.8.1.dist-info/METADATA
Wikidata-0.8.1.dist-info/WHEEL
Wikidata-0.8.1.dist-info/top_level.txt
Wikidata-0.8.1.dist-info/RECORD
