Metadata-Version: 2.1
Name: Wikidata
Version: 0.8.1
Summary: Wikidata client library
Home-page: https://github.com/dahlia/wikidata
Author: Hong Minhee
Author-email: hong.minhee@gmail.com
License: GPLv3 or later
Project-URL: Docs, https://wikidata.readthedocs.io/
Keywords: wikidata ontology
Platform: any
Classifier: Development Status :: 4 - Beta
Classifier: Intended Audience :: Developers
Classifier: Intended Audience :: Information Technology
Classifier: License :: OSI Approved :: GNU General Public License v3 or later (GPLv3+)
Classifier: Operating System :: OS Independent
Classifier: Programming Language :: Python :: 3
Classifier: Programming Language :: Python :: 3.8
Classifier: Programming Language :: Python :: 3.9
Classifier: Programming Language :: Python :: 3.10
Classifier: Programming Language :: Python :: 3.11
Classifier: Programming Language :: Python :: 3 :: Only
Classifier: Programming Language :: Python :: Implementation :: CPython
Classifier: Programming Language :: Python :: Implementation :: PyPy
Classifier: Topic :: Database
Classifier: Topic :: Internet :: WWW/HTTP
Classifier: Topic :: Scientific/Engineering
Classifier: Topic :: Software Development :: Libraries :: Python Modules
Requires-Python: >=3.8.0
License-File: LICENSE
Requires-Dist: typing; python_version < "3.5"
Provides-Extra: tests
Requires-Dist: flake8>=6.0.0; extra == "tests"
Requires-Dist: flake8-import-order-spoqa; extra == "tests"
Requires-Dist: pytest~=7.2.1; extra == "tests"
Requires-Dist: mypy>=0.991; extra == "tests"
Provides-Extra: docs
Requires-Dist: furo; extra == "docs"
Requires-Dist: rstcheck; extra == "docs"
Requires-Dist: Sphinx~=6.1.3; extra == "docs"
